seaborn_objects_recipes/__init__.py
seaborn_objects_recipes/recipes/__init__.py
seaborn_objects_recipes/recipes/line_label.py
seaborn_objects_recipes/recipes/lowess.py
seaborn_objects_recipes/recipes/plotting.py
seaborn_objects_recipes/recipes/rolling.py
seaborn_objects_recipes/recipes/straight_line.py
seaborn_objects_recipes-0.2.1.dist-info/METADATA
seaborn_objects_recipes-0.2.1.dist-info/WHEEL
seaborn_objects_recipes-0.2.1.dist-info/licenses/LICENSE
seaborn_objects_recipes-0.2.1.dist-info/RECORD
