Metadata-Version: 2.4
Name: seaborn_objects_recipes
Version: 0.2.1
Summary: A collection of recipes that can be used together with the seaborn library to create custom plots.
License: MIT
License-File: LICENSE
Keywords: seaborn,seaborn.objects,lowess,statsmodels,visualization
Author: Ofosu Osei
Author-email: goofosuosei@gmail.com
Requires-Python: >=3.9,<3.13
Classifier: Intended Audience :: Science/Research
Classifier: License :: OSI Approved :: MIT License
Classifier: Operating System :: OS Independent
Classifier: Programming Language :: Python :: 3
Classifier: Programming Language :: Python :: 3.9
Classifier: Programming Language :: Python :: 3.10
Classifier: Programming Language :: Python :: 3.11
Classifier: Programming Language :: Python :: 3.12
Classifier: Topic :: Scientific/Engineering :: Visualization
Requires-Dist: matplotlib (>=3.6)
Requires-Dist: numpy (>=1.22)
Requires-Dist: pandas (>=1.5)
Requires-Dist: seaborn (>=0.13)
Requires-Dist: statsmodels (>=0.14)
Project-URL: Homepage, https://github.com/oosei25/seaborn_objects_recipes
Project-URL: Repository, https://github.com/oosei25/seaborn_objects_recipes
